mkdocs_swangallery/__init__.py
mkdocs_swangallery/swangallery.py
mkdocs_swangallery-0.0.6.dist-info/LICENSE
mkdocs_swangallery-0.0.6.dist-info/METADATA
mkdocs_swangallery-0.0.6.dist-info/WHEEL
mkdocs_swangallery-0.0.6.dist-info/entry_points.txt
mkdocs_swangallery-0.0.6.dist-info/top_level.txt
mkdocs_swangallery-0.0.6.dist-info/RECORD
