Metadata-Version: 2.1
Name: mkdocs-swangallery
Version: 0.0.6
Summary: Plugin for MkDocs to genereate a SWAN Gallery
Home-page: https://github.com/swan-cern/mkdocs-swangallery
Author: Diogo Castro
Author-email: diogo.castro@cern.ch
License: BSD
Classifier: Development Status :: 5 - Production/Stable
Classifier: Environment :: Web Environment
Classifier: License :: OSI Approved :: GNU Affero General Public License v3
Classifier: Programming Language :: Python
Classifier: Topic :: Documentation
Classifier: Topic :: Software Development :: Documentation
Classifier: Topic :: Text Processing :: Markup :: HTML
License-File: LICENSE
Requires-Dist: mkdocs
Requires-Dist: nbconvert (>=7)
Requires-Dist: ipython-genutils
Requires-Dist: nbformat
Requires-Dist: bs4
